vafator/__init__.py
vafator/annotator.py
vafator/command_line.py
vafator/hatchet2bed.py
vafator/multiallelic_filter.py
vafator/pileups.py
vafator/ploidies.py
vafator/power.py
vafator/rank_sum_test.py
vafator/vafator2decifer.py
vafator/tests/__init__.py
vafator/tests/test_annotator.py
vafator/tests/test_hatchet2bed.py
vafator/tests/test_multiallelic_filter.py
vafator/tests/test_pileups.py
vafator/tests/test_ploidy_manager.py
vafator/tests/test_power_calculator.py
vafator/tests/test_rank_sum_test.py
vafator/tests/utils.py
vafator-2.2.2.dist-info/LICENSE
vafator-2.2.2.dist-info/METADATA
vafator-2.2.2.dist-info/WHEEL
vafator-2.2.2.dist-info/entry_points.txt
vafator-2.2.2.dist-info/top_level.txt
vafator-2.2.2.dist-info/RECORD
