Metadata-Version: 2.1
Name: vafator
Version: 2.2.2
Summary: Annotate a VCF file with AF, AD and DP from tumor and normal BAMs
Home-page: https://github.com/tron-bioinformatics/vafator
Author: TRON - Translational Oncology at the University Medical Center of the Johannes Gutenberg University Mainz- Computational Medicine group
Author-email: pablo.riesgoferreiro@tron-mainz.de
License: MIT
Classifier: Development Status :: 4 - Beta
Classifier: Intended Audience :: Healthcare Industry
Classifier: Intended Audience :: Science/Research
Classifier: Topic :: Scientific/Engineering :: Bio-Informatics
Classifier: Programming Language :: Python :: 3.7
Classifier: Programming Language :: Python :: 3.8
Classifier: Programming Language :: Python :: 3.9
Classifier: Programming Language :: Python :: 3.10
Classifier: Programming Language :: Python :: 3 :: Only
Classifier: License :: OSI Approved :: MIT License
Classifier: Operating System :: Unix
Requires-Python: >=3.7
License-File: LICENSE
Requires-Dist: pandas~=1.3.3
Requires-Dist: pysam~=0.19.1
Requires-Dist: cyvcf2~=0.30.14
Requires-Dist: logzero~=1.7.0
Requires-Dist: pybedtools~=0.9.0
Requires-Dist: numpy<2.0,>=1.20
Requires-Dist: scipy<2.0.0,>=1.0.0
